ulid_flake/__init__.py
ulid_flake/api.py
ulid_flake/base32.py
ulid_flake/cli.py
ulid_flake/consts.py
ulid_flake/scalable.py
ulid_flake-0.1.3.dist-info/AUTHORS.rst
ulid_flake-0.1.3.dist-info/LICENSE
ulid_flake-0.1.3.dist-info/METADATA
ulid_flake-0.1.3.dist-info/WHEEL
ulid_flake-0.1.3.dist-info/top_level.txt
ulid_flake-0.1.3.dist-info/RECORD
