Metadata-Version: 2.1
Name: ulid-flake
Version: 0.1.3
Summary: Ulid-Flake, A 64-bit ULID variant featuring Snowflake.
Author-email: abailinrun <abailinrun@gmail.com>
Maintainer-email: abailinrun <abailinrun@gmail.com>
License: MIT license
Project-URL: bugs, https://github.com/ulid-flake/python/issues
Project-URL: changelog, https://github.com/ulid-flake/python/blob/master/changelog.md
Project-URL: homepage, https://github.com/ulid-flake/python
Classifier: Programming Language :: Python :: 3
Classifier: License :: OSI Approved :: MIT License
Classifier: Operating System :: OS Independent
Requires-Python: >=3.8
License-File: LICENSE
License-File: AUTHORS.rst
Requires-Dist: typer
Provides-Extra: dev
Requires-Dist: coverage ; extra == 'dev'
Requires-Dist: mypy ; extra == 'dev'
Requires-Dist: pytest ; extra == 'dev'
Requires-Dist: ruff ; extra == 'dev'
